vaahai/README.md
vaahai/__init__.py
vaahai/agents/README.md
vaahai/agents/__init__.py
vaahai/agents/applications/README.md
vaahai/agents/applications/__init__.py
vaahai/agents/applications/framework_detection/__init__.py
vaahai/agents/applications/framework_detection/agent.py
vaahai/agents/applications/framework_detection/prompts/framework_detection.md
vaahai/agents/applications/hello_world/__init__.py
vaahai/agents/applications/hello_world/agent.py
vaahai/agents/applications/hello_world/prompts/greeting.md
vaahai/agents/applications/language_detection/__init__.py
vaahai/agents/applications/language_detection/agent.py
vaahai/agents/applications/language_detection/prompts/language_detection.md
vaahai/agents/base/__init__.py
vaahai/agents/base/agent_base.py
vaahai/agents/base/agent_factory.py
vaahai/agents/base/agent_registry.py
vaahai/agents/base/autogen_agent_base.py
vaahai/agents/base/group_chat_factory.py
vaahai/agents/config_loader.py
vaahai/agents/prompts/base_system.md
vaahai/agents/prompts/hello_world.md
vaahai/agents/schemas.py
vaahai/agents/utils/__init__.py
vaahai/agents/utils/group_chat_manager.py
vaahai/agents/utils/prompt_manager.py
vaahai/cli/README.md
vaahai/cli/__init__.py
vaahai/cli/commands/__init__.py
vaahai/cli/commands/audit/__init__.py
vaahai/cli/commands/audit/command.py
vaahai/cli/commands/chat/__init__.py
vaahai/cli/commands/chat/command.py
vaahai/cli/commands/config/__init__.py
vaahai/cli/commands/config/command.py
vaahai/cli/commands/core/__init__.py
vaahai/cli/commands/dev/__init__.py
vaahai/cli/commands/dev/prompts.py
vaahai/cli/commands/dev/showcase.py
vaahai/cli/commands/helloworld/__init__.py
vaahai/cli/commands/helloworld/command.py
vaahai/cli/commands/model/__init__.py
vaahai/cli/commands/model/command.py
vaahai/cli/commands/project/__init__.py
vaahai/cli/commands/review/__init__.py
vaahai/cli/commands/review/command.py
vaahai/cli/commands/version/__init__.py
vaahai/cli/commands/version/command.py
vaahai/cli/main.py
vaahai-0.2.24.dist-info/METADATA
vaahai-0.2.24.dist-info/WHEEL
vaahai-0.2.24.dist-info/entry_points.txt
vaahai-0.2.24.dist-info/RECORD
