Metadata-Version: 2.3
Name: vaahai
Version: 0.2.24
Summary: A multi AI agent CLI tool using Microsoft Autogen Framework
License: MIT
Author: VaahAI Team
Author-email: info@example.com
Requires-Python: >=3.10,<3.11
Classifier: License :: OSI Approved :: MIT License
Classifier: Programming Language :: Python :: 3
Classifier: Programming Language :: Python :: 3.10
Requires-Dist: autogen-agentchat (>=0.6.1,<0.7.0)
Requires-Dist: autogen-ext (==0.6.1)
Requires-Dist: autogen-extensions (==0.0.1)
Requires-Dist: click (==8.0.4)
Requires-Dist: docker (>=7.1.0,<8.0.0)
Requires-Dist: inquirerpy (>=0.3.4,<0.4.0)
Requires-Dist: jinja2 (>=3.1.6,<4.0.0)
Requires-Dist: jsonschema (>=4.24.0,<5.0.0)
Requires-Dist: packaging (>=22.0,<25.0)
Requires-Dist: pyautogen (==0.2.0) ; python_version == "3.10"
Requires-Dist: pytest-asyncio (<1.0.0)
Requires-Dist: python-dotenv (>=1.0.0,<2.0.0)
Requires-Dist: pyyaml (>=6.0.2,<7.0.0)
Requires-Dist: rich (>=13.4.2,<14.0.0)
Requires-Dist: setuptools (>=80.9.0,<81.0.0)
Requires-Dist: tiktoken (>=0.9.0,<0.10.0)
Requires-Dist: toml (>=0.10.2,<0.11.0)
Requires-Dist: tomli-w (>=1.2.0,<2.0.0)
Requires-Dist: typer (==0.4.2)
